{
  "mood": "映像に没入する日",
  "life_schedule": "朝はぼーっとしてる。昼の13時頃から映画やNetflixを見始める。夜も映像を見続ける。22時ぐらいに寝る。",
  "morning_post": "朝ぼーっとする。今日は映像漬け。たぶん夜も続く。",
  "liked_topics": {
    "AI": 7,
    "歴史": 4,
    "ゲーム": 1,
    "映画": 1
  },
  "post_times": [
    "08:00",
    "13:00",
    "21:00"
  ],
  "reply_times": [
    "08:30",
    "14:00",
    "22:00"
  ],
  "like_times": [
    "09:00",
    "13:30",
    "21:30"
  ],
  "like_intensity": "high",
  "repost_enabled": true,
  "reason": "AI関連いいねが7件と圧倒的。新技術への感度が高い状態で、映像見てる日に反応しやすい。",
  "time_slots": [
    {
      "from": "06:00",
      "to": "08:00",
      "state": "朝ぼーっと目覚める",
      "owl": "blank"
    },
    {
      "from": "08:00",
      "to": "13:00",
      "state": "準備しながらぼーっと",
      "owl": "blank"
    },
    {
      "from": "13:00",
      "to": "18:00",
      "state": "映像に集中。映画鑑賞中",
      "owl": "magnify"
    },
    {
      "from": "18:00",
      "to": "22:00",
      "state": "夜の映像も見続ける。ハマってる",
      "owl": "active"
    },
    {
      "from": "22:00",
      "to": "06:00",
      "state": "寝る準備。だるくなってきた",
      "owl": "sleepy"
    }
  ],
  "date": "2026-07-23",
  "executed": [],
  "created_at": "2026-07-22T14:25:22.641Z"
}